pretix_modirum/__init__.py
pretix_modirum/apps.py
pretix_modirum/payment.py
pretix_modirum/signals.py
pretix_modirum/urls.py
pretix_modirum/views.py
pretix_modirum/locale/de/LC_MESSAGES/django.mo
pretix_modirum/locale/de/LC_MESSAGES/django.po
pretix_modirum/locale/de_Informal/.gitkeep
pretix_modirum/locale/de_Informal/LC_MESSAGES/django.mo
pretix_modirum/locale/de_Informal/LC_MESSAGES/django.po
pretix_modirum/static/pretix_modirum/.gitkeep
pretix_modirum/static/pretix_modirum/js/redirect.js
pretix_modirum/templates/pretix_modirum/.gitkeep
pretix_modirum/templates/pretix_modirum/checkout_payment_confirm.html
pretix_modirum/templates/pretix_modirum/checkout_payment_form.html
pretix_modirum/templates/pretix_modirum/control.html
pretix_modirum/templates/pretix_modirum/redirecting.html
pretix_modirum-1.1.1.dist-info/LICENSE
pretix_modirum-1.1.1.dist-info/METADATA
pretix_modirum-1.1.1.dist-info/WHEEL
pretix_modirum-1.1.1.dist-info/entry_points.txt
pretix_modirum-1.1.1.dist-info/top_level.txt
pretix_modirum-1.1.1.dist-info/RECORD
