Metadata-Version: 2.1
Name: pretix-modirum
Version: 1.1.1
Summary: Integration for payment providers based on the Modirum platform
Author-email: pretix team <support@pretix.eu>
Maintainer-email: pretix team <support@pretix.eu>
License: Copyright 2019 Raphael Michel
Project-URL: homepage, https://code.rami.io/pretix/pretix-modirum
Keywords: pretix
Requires-Python: >=3.9
License-File: LICENSE
